LICENSE
MANIFEST.in
README.md
requirements.txt
setup.py
limcv/__init__.py
limcv/aircv.py
limcv/cal_confidence.py
limcv/error.py
limcv/keypoint_base.py
limcv/keypoint_matching.py
limcv/keypoint_matching_contrib.py
limcv/match.py
limcv/sift.py
limcv/template.py
limcv/template_matching.py
limcv/utils.py
limcv.egg-info/PKG-INFO
limcv.egg-info/SOURCES.txt
limcv.egg-info/dependency_links.txt
limcv.egg-info/requires.txt
limcv.egg-info/top_level.txt