Metadata-Version: 2.1
Name: limcv
Version: 1.2
Summary: UNKNOWN
Home-page: https://github.com/JamesChungZLL/limcv
Author: Lim Chung
Author-email: 923739605@qq.com
License: UNKNOWN
Platform: UNKNOWN
